{
  "date": "2023-07-19",
  "datetime": 1689724800,
  "files": [
    {
      "date": "2023-07-19",
      "datetime": 1689724800,
      "filename": "lineage-20.0-20230719-nightly-akari-signed.zip",
      "filepath": "/full/akari/20230719/lineage-20.0-20230719-nightly-akari-signed.zip",
      "sha1": "7b98d472922264fc5e92b64090185f3e3a54cd02",
      "sha256": "6509f673bbc6e08b52073143e7e4cfef22368e0d24ef76547d51af4612a95b60",
      "size": 805043852,
      "type": "nightly",
      "url": "https://mirrorbits.lineageos.org/full/akari/20230719/lineage-20.0-20230719-nightly-akari-signed.zip"
    },
    {
      "filename": "boot.img",
      "filepath": "/full/akari/20230719/boot.img",
      "sha1": "b91c6451723a60f0142105d9f31b64e2013fca0b",
      "sha256": "720755af9c9d5e6f4fff313728d838d70554063810285ca6f885d4fb35439054",
      "size": 67108864,
      "url": "https://mirrorbits.lineageos.org/full/akari/20230719/boot.img"
    },
    {
      "filename": "dtbo.img",
      "filepath": "/full/akari/20230719/dtbo.img",
      "sha1": "b5fa2a3962dc6e6db59111230f917feaade805fe",
      "sha256": "bdebcd34fd2673928fea1fe96a00787a80c25551dbcd258f3e492ecc98e4d411",
      "size": 8388608,
      "url": "https://mirrorbits.lineageos.org/full/akari/20230719/dtbo.img"
    },
    {
      "filename": "vbmeta.img",
      "filepath": "/full/akari/20230719/vbmeta.img",
      "sha1": "268a0bcf42c3c6246302bb30c933906c95410c75",
      "sha256": "618f875373243959be5b6cf24453577a649195084644ae0179ff3bef390d071d",
      "size": 8192,
      "url": "https://mirrorbits.lineageos.org/full/akari/20230719/vbmeta.img"
    }
  ],
  "type": "nightly",
  "version": "20.0"
}
