{
  "date": "2024-02-16",
  "datetime": 1708041600,
  "files": [
    {
      "date": "2024-02-16",
      "datetime": 1708041600,
      "filename": "lineage-20.0-20240216-nightly-akari-signed.zip",
      "filepath": "/full/akari/20240216/lineage-20.0-20240216-nightly-akari-signed.zip",
      "os_patch_level": "2024-02",
      "sha1": "c6dcb1e3ac1880a3d90240f8f3b21adc8dbf37a3",
      "sha256": "b486ac1ffb8a43b07dea8cfbe68f5867fb59a704228eca3c3924811508004b11",
      "size": 804885999,
      "type": "nightly",
      "url": "https://mirrorbits.lineageos.org/full/akari/20240216/lineage-20.0-20240216-nightly-akari-signed.zip"
    },
    {
      "filename": "boot.img",
      "filepath": "/full/akari/20240216/boot.img",
      "sha1": "77704b1ec6250960d608383c6dde006f528af39e",
      "sha256": "aa8b48fa30dd6e27ca6c8e914c4eda1057fc1cef4b1e6dfaaf6975e48757f147",
      "size": 67108864,
      "url": "https://mirrorbits.lineageos.org/full/akari/20240216/boot.img"
    },
    {
      "filename": "dtbo.img",
      "filepath": "/full/akari/20240216/dtbo.img",
      "sha1": "0a1c555ee8323476de18ef3886c327e64b007ffd",
      "sha256": "d0c9235ee4cfa4825a581890c83d33bcfc8a3c0417d3e91283eee9d2270bf278",
      "size": 8388608,
      "url": "https://mirrorbits.lineageos.org/full/akari/20240216/dtbo.img"
    },
    {
      "filename": "vbmeta.img",
      "filepath": "/full/akari/20240216/vbmeta.img",
      "sha1": "dbd793c0070b8702c2ad529f44ac2a29e34d7e74",
      "sha256": "7c530255ca42a4013c536e21542727dd021358c0b07efc916930c69bea1e8ac9",
      "size": 8192,
      "url": "https://mirrorbits.lineageos.org/full/akari/20240216/vbmeta.img"
    }
  ],
  "os_patch_level": "2024-02",
  "type": "nightly",
  "version": "20.0"
}
