{
  "date": "2025-02-07",
  "datetime": 1738886400,
  "files": [
    {
      "date": "2025-02-07",
      "datetime": 1738886400,
      "filename": "lineage-21.0-20250207-nightly-akari-signed.zip",
      "filepath": "/full/akari/20250207/lineage-21.0-20250207-nightly-akari-signed.zip",
      "os_patch_level": "2025-01",
      "sha1": "8dd8762676f79eb868b0ffd75f43da21e223c0c3",
      "sha256": "eb4ab1eae2ff659e3c22097b2ed7755c346e4105f41befa4f79b6b54613ebb11",
      "size": 942367673,
      "type": "nightly",
      "url": "https://mirrorbits.lineageos.org/full/akari/20250207/lineage-21.0-20250207-nightly-akari-signed.zip"
    },
    {
      "filename": "boot.img",
      "filepath": "/full/akari/20250207/boot.img",
      "sha1": "3fad33d4c6cb4d75d73985f41841891f748fb41b",
      "sha256": "56cf21d5eaa9dc4ca1d93504c4ffa54ebe1449fe6debcdb338c88c12e8eb7dcb",
      "size": 67108864,
      "url": "https://mirrorbits.lineageos.org/full/akari/20250207/boot.img"
    },
    {
      "filename": "dtbo.img",
      "filepath": "/full/akari/20250207/dtbo.img",
      "sha1": "656f782cfa0e1aeaabeff996acc226e42ced4c8b",
      "sha256": "15937b1b6e88aaae646298f199f4a67ab2efcd0c971c696ccc2ce51feaf7ff4d",
      "size": 8388608,
      "url": "https://mirrorbits.lineageos.org/full/akari/20250207/dtbo.img"
    },
    {
      "filename": "vbmeta.img",
      "filepath": "/full/akari/20250207/vbmeta.img",
      "sha1": "9de88b4767395c53bded731a9b392ecbc04e726a",
      "sha256": "fcb3f89b11f999f53d24223da088ff8efe9aa1ea21ac71a06dcbbb41425fb9ea",
      "size": 4096,
      "url": "https://mirrorbits.lineageos.org/full/akari/20250207/vbmeta.img"
    }
  ],
  "os_patch_level": "2025-01",
  "type": "nightly",
  "version": "21.0"
}
