{
  "date": "2026-05-15",
  "datetime": 1778824178,
  "files": [
    {
      "date": "2026-05-15",
      "datetime": 1778824178,
      "filename": "lineage-23.2-20260515-nightly-coral-signed.zip",
      "filepath": "/full/coral/20260515/lineage-23.2-20260515-nightly-coral-signed.zip",
      "os_patch_level": "2026-05-01",
      "sha1": "94d29e8372593737506371eb26d903d46410c9cd",
      "sha256": "841105c782833412d6b32fedec580dc61826c183d4123551e8fd4b76e5e1c64d",
      "size": 1324140592,
      "type": "nightly",
      "url": "https://mirrorbits.lineageos.org/full/coral/20260515/lineage-23.2-20260515-nightly-coral-signed.zip"
    },
    {
      "filename": "boot.img",
      "filepath": "/full/coral/20260515/boot.img",
      "sha1": "b43c1781bd6dc35d85557ccc638e50a655541097",
      "sha256": "6ce087510612bd45cd98e8d8e1835510703acad9557068ec7d91611b8e7db2d2",
      "size": 67108864,
      "url": "https://mirrorbits.lineageos.org/full/coral/20260515/boot.img"
    },
    {
      "filename": "dtbo.img",
      "filepath": "/full/coral/20260515/dtbo.img",
      "sha1": "787a3f108ee1a5e9cd2e93fae28ee1d3801221d1",
      "sha256": "f8d63e2c9c88486727c493dce0320807c7d4d354f57a8f428b724916c6df6020",
      "size": 8388608,
      "url": "https://mirrorbits.lineageos.org/full/coral/20260515/dtbo.img"
    },
    {
      "filename": "super_empty.img",
      "filepath": "/full/coral/20260515/super_empty.img",
      "sha1": "394e4849a848ac2bfe6e60b7c76035019f364bc4",
      "sha256": "12802f79aaeec9cd4a060ad35e394977b90f4dd94208876b16bc6ebf160d6f29",
      "size": 4848,
      "url": "https://mirrorbits.lineageos.org/full/coral/20260515/super_empty.img"
    },
    {
      "filename": "vbmeta.img",
      "filepath": "/full/coral/20260515/vbmeta.img",
      "sha1": "550dc94d1f54ee2cc699ff21d0090f855de99ce4",
      "sha256": "ace396fee2824aa98be80a603f100a4db8e195c0d712c564dec45673e0ae504e",
      "size": 4096,
      "url": "https://mirrorbits.lineageos.org/full/coral/20260515/vbmeta.img"
    }
  ],
  "os_patch_level": "2026-05-01",
  "type": "nightly",
  "version": "23.2"
}
