{
  "date": "2023-05-15",
  "datetime": 1684108800,
  "files": [
    {
      "date": "2023-05-15",
      "datetime": 1684108800,
      "filename": "lineage-20.0-20230515-nightly-d1-signed.zip",
      "filepath": "/full/d1/20230515/lineage-20.0-20230515-nightly-d1-signed.zip",
      "sha1": "e99aee90b9a6532d8512fe3856c7dc871c081160",
      "sha256": "c955ea2d2e2efbd370912853b47795ef261b8f047745f2bf21264b66aad063c0",
      "size": 933476614,
      "type": "nightly",
      "url": "https://mirrorbits.lineageos.org/full/d1/20230515/lineage-20.0-20230515-nightly-d1-signed.zip"
    },
    {
      "filename": "boot.img",
      "filepath": "/full/d1/20230515/boot.img",
      "sha1": "3fa664e5c6e6a965c3ce95e568824f208e04254c",
      "sha256": "451a5d8985a587a36e51305e26966d2bf1bd7ae4ebeccbecb6af695c4a5f8fa4",
      "size": 57671680,
      "url": "https://mirrorbits.lineageos.org/full/d1/20230515/boot.img"
    },
    {
      "filename": "dtbo.img",
      "filepath": "/full/d1/20230515/dtbo.img",
      "sha1": "77820a4dcb9a3243cfb9a2fe817c4db6405e385f",
      "sha256": "c732e13d1cc20229f35d4dc10a44173c2286ab005efc114737716147b7223758",
      "size": 8388608,
      "url": "https://mirrorbits.lineageos.org/full/d1/20230515/dtbo.img"
    },
    {
      "filename": "recovery.img",
      "filepath": "/full/d1/20230515/recovery.img",
      "sha1": "2158efa3536a39c997f13a7078c9b612f63ac7b0",
      "sha256": "4892bd13685894be2258e9f98ca9f2b6f3100b51f36ad98259f1a701c50896a3",
      "size": 67633152,
      "url": "https://mirrorbits.lineageos.org/full/d1/20230515/recovery.img"
    },
    {
      "filename": "vbmeta.img",
      "filepath": "/full/d1/20230515/vbmeta.img",
      "sha1": "8f5e8c34e541f722829cb456ddeb225040186616",
      "sha256": "7c42ef85cdc2a62c54c22c6a4841c48142bbc18750b03f992b180ba21e81c5b0",
      "size": 4096,
      "url": "https://mirrorbits.lineageos.org/full/d1/20230515/vbmeta.img"
    }
  ],
  "type": "nightly",
  "version": "20.0"
}
