{
  "date": "2026-07-16",
  "datetime": 1784179938,
  "files": [
    {
      "date": "2026-07-16",
      "datetime": 1784179938,
      "filename": "lineage-23.2-20260716-nightly-d1-signed.zip",
      "filepath": "/full/d1/20260716/lineage-23.2-20260716-nightly-d1-signed.zip",
      "os_patch_level": "2026-07-01",
      "os_sdk_level": 36,
      "ota_property_files": "metadata:69:323,metadata.pb:460:200                 ",
      "sha1": "e532fb81423d4f126b744d394413f47803bd02ec",
      "sha256": "d80c8a4ab0bf1b0f527b76ac14469887b7f3f6cc6a445b9f1a092c5aa59d55df",
      "size": 1155950857,
      "type": "nightly",
      "url": "https://mirrorbits.lineageos.org/full/d1/20260716/lineage-23.2-20260716-nightly-d1-signed.zip"
    },
    {
      "filename": "boot.img",
      "filepath": "/full/d1/20260716/boot.img",
      "sha1": "ad2a11bba644e2e871b07d881e49415d7cbad71e",
      "sha256": "aba1236652ffc7fc9bb0999f457cd629c8b0c10ba3ec2b307e7f64b7ea6f98ed",
      "size": 57671680,
      "url": "https://mirrorbits.lineageos.org/full/d1/20260716/boot.img"
    },
    {
      "filename": "dtb.img",
      "filepath": "/full/d1/20260716/dtb.img",
      "sha1": "0fdc152c1b7edbb129fb82e5736a12acd53798f2",
      "sha256": "c0e0de681306a0678a3b3dc23dfc7729f293c9bba66dbe2520f3c8e3187476f5",
      "size": 8388608,
      "url": "https://mirrorbits.lineageos.org/full/d1/20260716/dtb.img"
    },
    {
      "filename": "dtbo.img",
      "filepath": "/full/d1/20260716/dtbo.img",
      "sha1": "6b14291eca6ab5bdaba41fc8c2086dd78a9bbcaf",
      "sha256": "ede4b1e73c9e44b2897f7118872d4d9ce41b86072b55acff2e15865f4ba08c3a",
      "size": 8388608,
      "url": "https://mirrorbits.lineageos.org/full/d1/20260716/dtbo.img"
    },
    {
      "filename": "recovery.img",
      "filepath": "/full/d1/20260716/recovery.img",
      "sha1": "7f3dd53f5caac8cb13d92662b1eddb226ae843a6",
      "sha256": "8405eaa7ff40b136aa699806a6aa1ca56a5bc3086a35a053c7f67cbb70f17330",
      "size": 67633152,
      "url": "https://mirrorbits.lineageos.org/full/d1/20260716/recovery.img"
    },
    {
      "filename": "super_empty.img",
      "filepath": "/full/d1/20260716/super_empty.img",
      "sha1": "8039715b8e0a8476bf37c880fe4d3959a727756f",
      "sha256": "0d93d5ffb0bd58eb5606497c743c9dc5a461022264caa9e256b47b7d353f2169",
      "size": 4644,
      "url": "https://mirrorbits.lineageos.org/full/d1/20260716/super_empty.img"
    },
    {
      "filename": "vbmeta.img",
      "filepath": "/full/d1/20260716/vbmeta.img",
      "sha1": "ff50a65a8461f6c4b16bda1e23f20a77e7378dc2",
      "sha256": "9ee600084b328f8c32e38f04140073608b6e07cb13b8af20eab6442b2aede04b",
      "size": 8192,
      "url": "https://mirrorbits.lineageos.org/full/d1/20260716/vbmeta.img"
    }
  ],
  "type": "nightly",
  "version": "23.2"
}
