{
  "date": "2026-03-29",
  "datetime": 1774755961,
  "files": [
    {
      "date": "2026-03-29",
      "datetime": 1774755961,
      "filename": "lineage-23.2-20260329-nightly-d2s-signed.zip",
      "filepath": "/full/d2s/20260329/lineage-23.2-20260329-nightly-d2s-signed.zip",
      "os_patch_level": "2026-03-01",
      "sha1": "f1cae6b8cd533999ebc14cb5992101ac31409a91",
      "sha256": "e32187a45942c35786690ba3a1969fe29601cb6379afbec8ff4270668775fab8",
      "size": 1153552475,
      "type": "nightly",
      "url": "https://mirrorbits.lineageos.org/full/d2s/20260329/lineage-23.2-20260329-nightly-d2s-signed.zip"
    },
    {
      "filename": "boot.img",
      "filepath": "/full/d2s/20260329/boot.img",
      "sha1": "3a57a46cd22a0c088822ac2e3b88afe23db8484c",
      "sha256": "366c9f8bfb95b7657962d5e06cea0ab6f7276f3905640b1ae39a7c06b1312337",
      "size": 57671680,
      "url": "https://mirrorbits.lineageos.org/full/d2s/20260329/boot.img"
    },
    {
      "filename": "dtb.img",
      "filepath": "/full/d2s/20260329/dtb.img",
      "sha1": "afcf4be514c81d06d121e34ef7dc209e8ec1ae65",
      "sha256": "4a84c710c501cd3e82a6152ec9158796f251347839760fce8d84f97fb0d00bbe",
      "size": 8388608,
      "url": "https://mirrorbits.lineageos.org/full/d2s/20260329/dtb.img"
    },
    {
      "filename": "dtbo.img",
      "filepath": "/full/d2s/20260329/dtbo.img",
      "sha1": "1090455c533692c4d45638177d4afaab86d9eb2a",
      "sha256": "0b787e592a1629b8ec81fb1481fef2708894ef83f9b99ed00b4e7ea47773247c",
      "size": 8388608,
      "url": "https://mirrorbits.lineageos.org/full/d2s/20260329/dtbo.img"
    },
    {
      "filename": "recovery.img",
      "filepath": "/full/d2s/20260329/recovery.img",
      "sha1": "e5541b461c368306bfa74376563d6606ed7bf4ff",
      "sha256": "948791f7898b6ffebc51484dece54cb72d1407e14c1ca6523992273f4c37c183",
      "size": 67633152,
      "url": "https://mirrorbits.lineageos.org/full/d2s/20260329/recovery.img"
    },
    {
      "filename": "super_empty.img",
      "filepath": "/full/d2s/20260329/super_empty.img",
      "sha1": "8039715b8e0a8476bf37c880fe4d3959a727756f",
      "sha256": "0d93d5ffb0bd58eb5606497c743c9dc5a461022264caa9e256b47b7d353f2169",
      "size": 4644,
      "url": "https://mirrorbits.lineageos.org/full/d2s/20260329/super_empty.img"
    },
    {
      "filename": "vbmeta.img",
      "filepath": "/full/d2s/20260329/vbmeta.img",
      "sha1": "30b92884670d9351a85a0472644a6394e3d10d26",
      "sha256": "6629cec872d22b5d829c6c08b0ddbdb0d838f07f8236087ca793f0526f2e7f2b",
      "size": 8192,
      "url": "https://mirrorbits.lineageos.org/full/d2s/20260329/vbmeta.img"
    }
  ],
  "os_patch_level": "2026-03-01",
  "type": "nightly",
  "version": "23.2"
}
