{
  "date": "2025-07-18",
  "datetime": 1752796800,
  "files": [
    {
      "date": "2025-07-18",
      "datetime": 1752796800,
      "filename": "lineage-22.2-20250718-nightly-dre-signed.zip",
      "filepath": "/full/dre/20250718/lineage-22.2-20250718-nightly-dre-signed.zip",
      "os_patch_level": "2025-07",
      "sha1": "a0d18a522287caf943c5b3a86eafc65a7e79d90a",
      "sha256": "75db1dfa4d6b9c5ad4ecc79478e429c236a405014c1bfd721ed01288f66acc59",
      "size": 1238277501,
      "type": "nightly",
      "url": "https://mirrorbits.lineageos.org/full/dre/20250718/lineage-22.2-20250718-nightly-dre-signed.zip"
    },
    {
      "filename": "boot.img",
      "filepath": "/full/dre/20250718/boot.img",
      "sha1": "828b0c34bb469701fcc4feb82243a906ecb630e3",
      "sha256": "699f2259ceec75eca7de9b84b0eecbd2435b3626119f10e3d3c0f4d6175122a2",
      "size": 100663296,
      "url": "https://mirrorbits.lineageos.org/full/dre/20250718/boot.img"
    },
    {
      "filename": "dtbo.img",
      "filepath": "/full/dre/20250718/dtbo.img",
      "sha1": "151e0d137e0ceaa5647b059a60e3b7217777ae64",
      "sha256": "0e27d8064ae2f14092ad881c3208532e63adc055447a79ad27767d906be6cde2",
      "size": 8388608,
      "url": "https://mirrorbits.lineageos.org/full/dre/20250718/dtbo.img"
    },
    {
      "filename": "super_empty.img",
      "filepath": "/full/dre/20250718/super_empty.img",
      "sha1": "58be45889fca6cb907dabd0a59123773ce25c110",
      "sha256": "0591d3800b0922e688d870ea0bd2599412aa611da1d142eb21cebf62de476fa2",
      "size": 5184,
      "url": "https://mirrorbits.lineageos.org/full/dre/20250718/super_empty.img"
    },
    {
      "filename": "vbmeta.img",
      "filepath": "/full/dre/20250718/vbmeta.img",
      "sha1": "d2e62539ebe6277291688e8cd49381a27f16de31",
      "sha256": "b3af616aee08315dd75f0589a3fa0cc4d3002c1f0633693165bd3cd469168c24",
      "size": 8192,
      "url": "https://mirrorbits.lineageos.org/full/dre/20250718/vbmeta.img"
    },
    {
      "filename": "vendor_boot.img",
      "filepath": "/full/dre/20250718/vendor_boot.img",
      "sha1": "d0d5717da82cbf99de94cd7c501eeb41e86e09fc",
      "sha256": "3e54f8ae260072eca5558d8b92c84d6f54f3b2e42ce558052537358ff92b33af",
      "size": 100663296,
      "url": "https://mirrorbits.lineageos.org/full/dre/20250718/vendor_boot.img"
    }
  ],
  "os_patch_level": "2025-07",
  "type": "nightly",
  "version": "22.2"
}
