{
  "date": "2025-09-12",
  "datetime": 1757635200,
  "files": [
    {
      "date": "2025-09-12",
      "datetime": 1757635200,
      "filename": "lineage-22.2-20250912-nightly-f62-signed.zip",
      "filepath": "/full/f62/20250912/lineage-22.2-20250912-nightly-f62-signed.zip",
      "os_patch_level": "2025-08",
      "sha1": "80f44008164c47235e49a9341f2cbbcc6c005c49",
      "sha256": "9dbeb8a216735a5e88b712c0c9b21834eb7d7785a3c461791509b7f58125c8a6",
      "size": 1099148676,
      "type": "nightly",
      "url": "https://mirrorbits.lineageos.org/full/f62/20250912/lineage-22.2-20250912-nightly-f62-signed.zip"
    },
    {
      "filename": "boot.img",
      "filepath": "/full/f62/20250912/boot.img",
      "sha1": "3e68ecc834be81cc98b42d7a55d92817d024054a",
      "sha256": "c63b947b7c01a664c0ac2c6dc92eee0d65929f0f994cb852002b26612ef61101",
      "size": 61865984,
      "url": "https://mirrorbits.lineageos.org/full/f62/20250912/boot.img"
    },
    {
      "filename": "dtbo.img",
      "filepath": "/full/f62/20250912/dtbo.img",
      "sha1": "4914ca7c837deb7a264fe2fc467570ea1db94960",
      "sha256": "d14ab889befaebfb3b4f9f060cc94375eeb573f37d389528ca1e463358d8bf6b",
      "size": 8388608,
      "url": "https://mirrorbits.lineageos.org/full/f62/20250912/dtbo.img"
    },
    {
      "filename": "recovery.img",
      "filepath": "/full/f62/20250912/recovery.img",
      "sha1": "0593d069ce6de85900889dd100a9701ba215f848",
      "sha256": "b3d3a3a930f96d9e43a9c897f20626d343540970d727fc25b50311362f1f21c5",
      "size": 71102464,
      "url": "https://mirrorbits.lineageos.org/full/f62/20250912/recovery.img"
    },
    {
      "filename": "super_empty.img",
      "filepath": "/full/f62/20250912/super_empty.img",
      "sha1": "578f38b9f9ab98d2f2a13facd346df98056eda91",
      "sha256": "4394e355c936059034d88d292f67e81da9639a0e6ed526831bfaa90d9253940e",
      "size": 4644,
      "url": "https://mirrorbits.lineageos.org/full/f62/20250912/super_empty.img"
    },
    {
      "filename": "vbmeta.img",
      "filepath": "/full/f62/20250912/vbmeta.img",
      "sha1": "e06735ae17abc6504a58f2fcbf36747d26a26dde",
      "sha256": "e1b069925848715c2d93ea66b1636870a8771e93a9114b4b7558b40f486d3026",
      "size": 4096,
      "url": "https://mirrorbits.lineageos.org/full/f62/20250912/vbmeta.img"
    }
  ],
  "os_patch_level": "2025-08",
  "type": "nightly",
  "version": "22.2"
}
