{
  "date": "2024-09-05",
  "datetime": 1725494400,
  "files": [
    {
      "date": "2024-09-05",
      "datetime": 1725494400,
      "filename": "lineage-21.0-20240905-nightly-flame-signed.zip",
      "filepath": "/full/flame/20240905/lineage-21.0-20240905-nightly-flame-signed.zip",
      "os_patch_level": "2024-08",
      "sha1": "2fc5c35f2f6ec5b3cfb7a6f3df3bf081139a44a7",
      "sha256": "8af1a59937f5629ef80473f46ffc540f9e4850442d746afa49e7a89a6dab2a01",
      "size": 1246859188,
      "type": "nightly",
      "url": "https://mirrorbits.lineageos.org/full/flame/20240905/lineage-21.0-20240905-nightly-flame-signed.zip"
    },
    {
      "filename": "boot.img",
      "filepath": "/full/flame/20240905/boot.img",
      "sha1": "c3fc0a78501abd180ff6a04bc610454698c5a700",
      "sha256": "93349f0876f66ba33a8c655294ece1d76ac708b100021c61445fbb197507107e",
      "size": 67108864,
      "url": "https://mirrorbits.lineageos.org/full/flame/20240905/boot.img"
    },
    {
      "filename": "dtbo.img",
      "filepath": "/full/flame/20240905/dtbo.img",
      "sha1": "8f1ff42d85d75d2f19e3a8632d97692929b34d91",
      "sha256": "989aa76528216d00dc0601556a473f47d5b40ef8c06fb7888e4d329acb2d9741",
      "size": 8388608,
      "url": "https://mirrorbits.lineageos.org/full/flame/20240905/dtbo.img"
    },
    {
      "filename": "super_empty.img",
      "filepath": "/full/flame/20240905/super_empty.img",
      "sha1": "89fa029b4b985982dbc834f09845025422714c97",
      "sha256": "3cd413454b2259ac22de1539dd568f1fcc4dbebbd611e457322863ea82170e2a",
      "size": 4848,
      "url": "https://mirrorbits.lineageos.org/full/flame/20240905/super_empty.img"
    },
    {
      "filename": "vbmeta.img",
      "filepath": "/full/flame/20240905/vbmeta.img",
      "sha1": "a7fb9628ef266523690df5ae109355e4157cb0c1",
      "sha256": "e8921db8c507b1d30e5f050e6278f562210e39b97fcfaebbea00f850aa74123a",
      "size": 4096,
      "url": "https://mirrorbits.lineageos.org/full/flame/20240905/vbmeta.img"
    }
  ],
  "os_patch_level": "2024-08",
  "type": "nightly",
  "version": "21.0"
}
