{
  "date": "2023-12-06",
  "datetime": 1701820800,
  "files": [
    {
      "date": "2023-12-06",
      "datetime": 1701820800,
      "filename": "lineage-20.0-20231206-nightly-FP3-signed.zip",
      "filepath": "/full/FP3/20231206/lineage-20.0-20231206-nightly-FP3-signed.zip",
      "sha1": "21438c88d5679f0a7839591e49d518eb44819063",
      "sha256": "b6fe6cbdb9e9550812e9615f6935674a65a7f0dbe36896e2c7c97b0bb4cf91e9",
      "size": 869023778,
      "type": "nightly",
      "url": "https://mirrorbits.lineageos.org/full/FP3/20231206/lineage-20.0-20231206-nightly-FP3-signed.zip"
    },
    {
      "filename": "boot.img",
      "filepath": "/full/FP3/20231206/boot.img",
      "sha1": "f7fb6ee6dbd2f3fe7712acc92856075a00555645",
      "sha256": "211dad24fc94af3252259afd67df8e26dcc694a5e0bbc7e621529882daa04751",
      "size": 67108864,
      "url": "https://mirrorbits.lineageos.org/full/FP3/20231206/boot.img"
    },
    {
      "filename": "dtbo.img",
      "filepath": "/full/FP3/20231206/dtbo.img",
      "sha1": "76137b037167dbd0280a6d58f1e00ce63fd1fd42",
      "sha256": "3b19bebf04121d7bb95a50bf8f162e373102f6eecd5be87b74bd9bc9e0d6534c",
      "size": 8388608,
      "url": "https://mirrorbits.lineageos.org/full/FP3/20231206/dtbo.img"
    },
    {
      "filename": "vbmeta.img",
      "filepath": "/full/FP3/20231206/vbmeta.img",
      "sha1": "7ca12d367d3223d5466e9294e5ee94d9f1b57c94",
      "sha256": "3685f5daa7b2b5c8cf4c54e295cdaa6d3a7e11078bcfc603e8c63008a9c51f1a",
      "size": 4096,
      "url": "https://mirrorbits.lineageos.org/full/FP3/20231206/vbmeta.img"
    }
  ],
  "type": "nightly",
  "version": "20.0"
}
