{
  "date": "2026-06-17",
  "datetime": 1781693509,
  "files": [
    {
      "date": "2026-06-17",
      "datetime": 1781693509,
      "filename": "lineage-23.2-20260617-nightly-FP4-signed.zip",
      "filepath": "/full/FP4/20260617/lineage-23.2-20260617-nightly-FP4-signed.zip",
      "os_patch_level": "2026-06-01",
      "os_sdk_level": 36,
      "ota_property_files": "payload_metadata.bin:4130:131509,payload.bin:4130:1235983489,payload_properties.txt:1235987677:156,apex_info.pb:1884:1279,care_map.pb:3210:873,metadata:69:666,metadata.pb:803:1033                        ",
      "sha1": "8caddaf38a7e7b892fa17964d16af8dd8ab35d9d",
      "sha256": "7871197a5283ff0fe20950b81f5ff8eb52d031af433660c085eb961baaff8b15",
      "size": 1235990824,
      "type": "nightly",
      "url": "https://mirrorbits.lineageos.org/full/FP4/20260617/lineage-23.2-20260617-nightly-FP4-signed.zip"
    },
    {
      "filename": "boot.img",
      "filepath": "/full/FP4/20260617/boot.img",
      "sha1": "93aa33c8a572dc1d86fc46c852e7a2768cef0bac",
      "sha256": "39fe94ded39df2a5c4e5c5cfdab245b899c5aca4f28d75a70ad78d6d1a0e5e97",
      "size": 100663296,
      "url": "https://mirrorbits.lineageos.org/full/FP4/20260617/boot.img"
    },
    {
      "filename": "dtbo.img",
      "filepath": "/full/FP4/20260617/dtbo.img",
      "sha1": "57e42ba49130d5ceee627ebdcbe310011b2302e0",
      "sha256": "1c020f17c9a37fa5aa06871e3882167388b29424208f063e7f0e5d0bcca37353",
      "size": 25165824,
      "url": "https://mirrorbits.lineageos.org/full/FP4/20260617/dtbo.img"
    },
    {
      "filename": "recovery.img",
      "filepath": "/full/FP4/20260617/recovery.img",
      "sha1": "24e772d340239c1b4f2280d86b4d0b15139eba8b",
      "sha256": "3765224dfe5523e7b70025609098cf1863bb083b029d66cd9f34d558caed3236",
      "size": 100663296,
      "url": "https://mirrorbits.lineageos.org/full/FP4/20260617/recovery.img"
    },
    {
      "filename": "super_empty.img",
      "filepath": "/full/FP4/20260617/super_empty.img",
      "sha1": "094cccd50541e2cb663a8a28dff2ebd0c45fc5ed",
      "sha256": "609e03dd1288b6e0b26ab26add4060789c938b66f51ceec11eeafa988b06212a",
      "size": 5080,
      "url": "https://mirrorbits.lineageos.org/full/FP4/20260617/super_empty.img"
    },
    {
      "filename": "vbmeta.img",
      "filepath": "/full/FP4/20260617/vbmeta.img",
      "sha1": "96e0570877a57da108165c81f1b926adb608f633",
      "sha256": "1df398a977bbb04a651c8c31d87e14e971c7c7f23061284593b1cd213f0528c1",
      "size": 8192,
      "url": "https://mirrorbits.lineageos.org/full/FP4/20260617/vbmeta.img"
    }
  ],
  "os_patch_level": "2026-06-01",
  "os_sdk_level": 36,
  "ota_property_files": "payload_metadata.bin:4130:131509,payload.bin:4130:1235983489,payload_properties.txt:1235987677:156,apex_info.pb:1884:1279,care_map.pb:3210:873,metadata:69:666,metadata.pb:803:1033                        ",
  "type": "nightly",
  "version": "23.2"
}
