{
  "date": "2023-05-31",
  "datetime": 1685491200,
  "files": [
    {
      "date": "2023-05-31",
      "datetime": 1685491200,
      "filename": "lineage-19.1-20230531-nightly-h830-signed.zip",
      "filepath": "/full/h830/20230531/lineage-19.1-20230531-nightly-h830-signed.zip",
      "sha1": "6d7c90b75f399ad8a8ea6bc190804519ab66e3ef",
      "sha256": "b99739e1b808afffb1516e1a01e6a2a91c5205b444fea05a750d92d7c3e00a7d",
      "size": 759343679,
      "type": "nightly",
      "url": "https://mirrorbits.lineageos.org/full/h830/20230531/lineage-19.1-20230531-nightly-h830-signed.zip"
    },
    {
      "filename": "boot.img",
      "filepath": "/full/h830/20230531/boot.img",
      "sha1": "e638994ceb6b235952a790e9ab47e7323a79cf2a",
      "sha256": "2fbe48a6ce53be2e665af9112758b6062e69fb2741ecb185da3b5ead013969d0",
      "size": 14643200,
      "url": "https://mirrorbits.lineageos.org/full/h830/20230531/boot.img"
    },
    {
      "filename": "recovery.img",
      "filepath": "/full/h830/20230531/recovery.img",
      "sha1": "63f71e395601b0e9e3b217f2621cbb9ead018940",
      "sha256": "3b52c07726723056d511dce70c899f21b5a42a9bafb367a8fb47f5f160bec2f5",
      "size": 20353024,
      "url": "https://mirrorbits.lineageos.org/full/h830/20230531/recovery.img"
    }
  ],
  "type": "nightly",
  "version": "19.1"
}
