{
  "date": "2024-02-04",
  "datetime": 1707004800,
  "files": [
    {
      "date": "2024-02-04",
      "datetime": 1707004800,
      "filename": "lineage-20.0-20240204-nightly-h932-signed.zip",
      "filepath": "/full/h932/20240204/lineage-20.0-20240204-nightly-h932-signed.zip",
      "os_patch_level": "2024-01",
      "sha1": "bbb78c8a782d7708ab49f2f16b9d266a0c525710",
      "sha256": "441df1bfb1b48808eaaf0730dc7df6f3df5ecafcf6805cf319ef81932d122fcb",
      "size": 870683637,
      "type": "nightly",
      "url": "https://mirrorbits.lineageos.org/full/h932/20240204/lineage-20.0-20240204-nightly-h932-signed.zip"
    },
    {
      "filename": "boot.img",
      "filepath": "/full/h932/20240204/boot.img",
      "sha1": "39371ad69cbbb8501241b3d060ca1584d45bc9fa",
      "sha256": "a6faff92aeccc03d7474bdfd4ea7a2ec15f0f2d6c92cee9e98432e4f75ccbd0d",
      "size": 20021248,
      "url": "https://mirrorbits.lineageos.org/full/h932/20240204/boot.img"
    },
    {
      "filename": "recovery.img",
      "filepath": "/full/h932/20240204/recovery.img",
      "sha1": "77c4f93c1c2f426f8ce073acf92bded8ad9577a6",
      "sha256": "160acfa2f6ec6402ae0728d8aead1cc6da337d39b07cccfe270dabde24e99263",
      "size": 31404032,
      "url": "https://mirrorbits.lineageos.org/full/h932/20240204/recovery.img"
    }
  ],
  "os_patch_level": "2024-01",
  "type": "nightly",
  "version": "20.0"
}
