{
  "date": "2026-05-03",
  "datetime": 1777781146,
  "files": [
    {
      "date": "2026-05-03",
      "datetime": 1777781146,
      "filename": "lineage-22.2-20260503-nightly-joan-signed.zip",
      "filepath": "/full/joan/20260503/lineage-22.2-20260503-nightly-joan-signed.zip",
      "os_patch_level": "2026-04-01",
      "sha1": "e56c8eac380b4d3f11abaa42e1f2ebed07ad6e7e",
      "sha256": "0c6fbc12ad240a90363c18b69fa1367c95806d3b66d3bf385a2166a9c17d1c0a",
      "size": 1042755893,
      "type": "nightly",
      "url": "https://mirrorbits.lineageos.org/full/joan/20260503/lineage-22.2-20260503-nightly-joan-signed.zip"
    },
    {
      "filename": "boot.img",
      "filepath": "/full/joan/20260503/boot.img",
      "sha1": "42554d2b5ae99bbd03ca54e9e808b282e72a7658",
      "sha256": "3135a72915241ef0d69dbe489b5f63be8c7094c702d4ceee754d0d069982e9ca",
      "size": 20402176,
      "url": "https://mirrorbits.lineageos.org/full/joan/20260503/boot.img"
    },
    {
      "filename": "recovery.img",
      "filepath": "/full/joan/20260503/recovery.img",
      "sha1": "690fde472ad609a9076f382ef35326942b68011a",
      "sha256": "4ef2fbc51c20893216c453c65914f9c12d08006d324d36bd1c3f1f6f41a8ec26",
      "size": 34107392,
      "url": "https://mirrorbits.lineageos.org/full/joan/20260503/recovery.img"
    },
    {
      "filename": "super_empty.img",
      "filepath": "/full/joan/20260503/super_empty.img",
      "sha1": "04b3b55648bd1e44f01209c1e43f0c58759fa36e",
      "sha256": "f739c1c94e587cd309992dd0da0948568b3ad0ec6de150203de35a79ba0a09df",
      "size": 4644,
      "url": "https://mirrorbits.lineageos.org/full/joan/20260503/super_empty.img"
    }
  ],
  "os_patch_level": "2026-04-01",
  "type": "nightly",
  "version": "22.2"
}
