{
  "date": "2023-10-27",
  "datetime": 1698364800,
  "files": [
    {
      "date": "2023-10-27",
      "datetime": 1698364800,
      "filename": "lineage-19.1-20231027-nightly-kirin-signed.zip",
      "filepath": "/full/kirin/20231027/lineage-19.1-20231027-nightly-kirin-signed.zip",
      "sha1": "05028be7313e8f4e4685ec22e1c2a35847d1dc4e",
      "sha256": "ce601f45333603910c154fa7b8760d7a1fb20ecf64aed449e4ae8be55c2afec2",
      "size": 701118166,
      "type": "nightly",
      "url": "https://mirrorbits.lineageos.org/full/kirin/20231027/lineage-19.1-20231027-nightly-kirin-signed.zip"
    },
    {
      "filename": "boot.img",
      "filepath": "/full/kirin/20231027/boot.img",
      "sha1": "4cad55fdc00c296e7bfa758901f8f5c3d51f85bf",
      "sha256": "0148e35a42080003044f1ba5825f222892d18098586e318d0b77192365197ab9",
      "size": 24958248,
      "url": "https://mirrorbits.lineageos.org/full/kirin/20231027/boot.img"
    }
  ],
  "type": "nightly",
  "version": "19.1"
}
