{
  "date": "2023-09-26",
  "datetime": 1695686400,
  "files": [
    {
      "date": "2023-09-26",
      "datetime": 1695686400,
      "filename": "lineage-20.0-20230926-nightly-lake-signed.zip",
      "filepath": "/full/lake/20230926/lineage-20.0-20230926-nightly-lake-signed.zip",
      "sha1": "7f9da88ff3f09b183d389c1ffe8ffefa5da57765",
      "sha256": "d05974221fb3e01cc6eae6461be72ed2151d6192dffb7c3ac39f914bf2e84101",
      "size": 789708811,
      "type": "nightly",
      "url": "https://mirrorbits.lineageos.org/full/lake/20230926/lineage-20.0-20230926-nightly-lake-signed.zip"
    },
    {
      "filename": "boot.img",
      "filepath": "/full/lake/20230926/boot.img",
      "sha1": "fa429f2a3e44afc33acd0266dcb4906d97121af1",
      "sha256": "3f03b65e84bc42a0fc25f548fa354e25aff1801aac8f8dec5d183d91a3107bd3",
      "size": 26813736,
      "url": "https://mirrorbits.lineageos.org/full/lake/20230926/boot.img"
    },
    {
      "filename": "dtbo.img",
      "filepath": "/full/lake/20230926/dtbo.img",
      "sha1": "0a60577015eb6a91b218fb54442cd9c0e4768bfd",
      "sha256": "51ca2b91984cb6dfc751dfaab819b7307498d47043aaf4e35b75cb180ece1a07",
      "size": 8939,
      "url": "https://mirrorbits.lineageos.org/full/lake/20230926/dtbo.img"
    }
  ],
  "type": "nightly",
  "version": "20.0"
}
