{
  "date": "2024-12-17",
  "datetime": 1734393600,
  "files": [
    {
      "date": "2024-12-17",
      "datetime": 1734393600,
      "filename": "lineage-21.0-20241217-nightly-lisa-signed.zip",
      "filepath": "/full/lisa/20241217/lineage-21.0-20241217-nightly-lisa-signed.zip",
      "os_patch_level": "2024-12",
      "sha1": "75c52d067a716c93c373e60595db250da74681bf",
      "sha256": "7e3012c82377a31bd54f5df18680a4c5b88ace501ee29bd5589dc11cc333df2b",
      "size": 1320579315,
      "type": "nightly",
      "url": "https://mirrorbits.lineageos.org/full/lisa/20241217/lineage-21.0-20241217-nightly-lisa-signed.zip"
    },
    {
      "filename": "boot.img",
      "filepath": "/full/lisa/20241217/boot.img",
      "sha1": "290285f37c82ae38687da79d240011eade7ba11e",
      "sha256": "ba0cff02d7910beefcce311778646159fc6dd0c072230253a0b4d67314ef7171",
      "size": 201326592,
      "url": "https://mirrorbits.lineageos.org/full/lisa/20241217/boot.img"
    },
    {
      "filename": "dtbo.img",
      "filepath": "/full/lisa/20241217/dtbo.img",
      "sha1": "588464f4b33391900dd05666624f85f41cfee8c6",
      "sha256": "cbb5d7dd397e79d22b053d5f65cd254127fa641c76ae7a89879e8386a590c4b5",
      "size": 25165824,
      "url": "https://mirrorbits.lineageos.org/full/lisa/20241217/dtbo.img"
    },
    {
      "filename": "super_empty.img",
      "filepath": "/full/lisa/20241217/super_empty.img",
      "sha1": "26a3bb85fb968f2464dda48b1ada4b31ce591bff",
      "sha256": "65b580a751bab05f7b69d3859a6a88dac3426a7f91ad1209924c5ec92a5706d3",
      "size": 5184,
      "url": "https://mirrorbits.lineageos.org/full/lisa/20241217/super_empty.img"
    },
    {
      "filename": "vbmeta.img",
      "filepath": "/full/lisa/20241217/vbmeta.img",
      "sha1": "d4f229cad238ffef7bba7fcbf4cc917faee6f76d",
      "sha256": "34c7d9edc97845e30f7f40725525cfbaf0b7273c27143eb0e989012153aed2b1",
      "size": 8192,
      "url": "https://mirrorbits.lineageos.org/full/lisa/20241217/vbmeta.img"
    },
    {
      "filename": "vendor_boot.img",
      "filepath": "/full/lisa/20241217/vendor_boot.img",
      "sha1": "4439fd0889d9b83c5bfa304f07c4527c41067582",
      "sha256": "2fadd0199f01665c5b63bc964f4c2849c152c77785c374856f2b240b3e1f52dc",
      "size": 100663296,
      "url": "https://mirrorbits.lineageos.org/full/lisa/20241217/vendor_boot.img"
    }
  ],
  "os_patch_level": "2024-12",
  "type": "nightly",
  "version": "21.0"
}
