{
  "date": "2026-05-06",
  "datetime": 1778068536,
  "files": [
    {
      "date": "2026-05-06",
      "datetime": 1778068536,
      "filename": "lineage-22.2-20260506-nightly-nash-signed.zip",
      "filepath": "/full/nash/20260506/lineage-22.2-20260506-nightly-nash-signed.zip",
      "os_patch_level": "2026-05-01",
      "sha1": "c42a4a4cd147c13f6859c8528afb8bb0d1f653da",
      "sha256": "b9c7129543ba55769039b62ce71bdbf944d70dc0b392df74aebd4f9c0c24eb23",
      "size": 897600823,
      "type": "nightly",
      "url": "https://mirrorbits.lineageos.org/full/nash/20260506/lineage-22.2-20260506-nightly-nash-signed.zip"
    },
    {
      "filename": "boot.img",
      "filepath": "/full/nash/20260506/boot.img",
      "sha1": "f23d2e0a960e25a54b81425d4d810c01a60c7c2e",
      "sha256": "f0cf712932796bed2a338b3834dbdf52bb41aa647c2d2612a498d05e5cd47ae6",
      "size": 33021952,
      "url": "https://mirrorbits.lineageos.org/full/nash/20260506/boot.img"
    }
  ],
  "os_patch_level": "2026-05-01",
  "type": "nightly",
  "version": "22.2"
}
