{
  "date": "2023-08-22",
  "datetime": 1692662400,
  "files": [
    {
      "date": "2023-08-22",
      "datetime": 1692662400,
      "filename": "lineage-20.0-20230822-nightly-PL2-signed.zip",
      "filepath": "/full/PL2/20230822/lineage-20.0-20230822-nightly-PL2-signed.zip",
      "sha1": "6c9193b8db84842f38aed6e4611ecffdb4052274",
      "sha256": "5cd5ea7d8c478d3c8725160b407f24f3f545842dcce7519d9254938d8fe5a2b3",
      "size": 834408879,
      "type": "nightly",
      "url": "https://mirrorbits.lineageos.org/full/PL2/20230822/lineage-20.0-20230822-nightly-PL2-signed.zip"
    },
    {
      "filename": "boot.img",
      "filepath": "/full/PL2/20230822/boot.img",
      "sha1": "b724739986363a841df281259c7ca7f85aa8c2cb",
      "sha256": "41ca25a8898fee1a31fda0c9b0502c694c7e98379321f10fb2b671cc9cc134de",
      "size": 41600296,
      "url": "https://mirrorbits.lineageos.org/full/PL2/20230822/boot.img"
    }
  ],
  "type": "nightly",
  "version": "20.0"
}
