{
  "date": "2025-09-13",
  "datetime": 1757721600,
  "files": [
    {
      "date": "2025-09-13",
      "datetime": 1757721600,
      "filename": "lineage-22.2-20250913-nightly-r8q-signed.zip",
      "filepath": "/full/r8q/20250913/lineage-22.2-20250913-nightly-r8q-signed.zip",
      "os_patch_level": "2025-08",
      "sha1": "6a424e24b7310c2fc9ee5999a1f5a573ab5f37ac",
      "sha256": "361fc15688948bd741be44aae1b0ffae0f2b369881d3e569c379ec82c1516d0f",
      "size": 1226279554,
      "type": "nightly",
      "url": "https://mirrorbits.lineageos.org/full/r8q/20250913/lineage-22.2-20250913-nightly-r8q-signed.zip"
    },
    {
      "filename": "boot.img",
      "filepath": "/full/r8q/20250913/boot.img",
      "sha1": "e6cbc2d3cf1247f6bddb7ef20f130dcba39d4957",
      "sha256": "5b7feb14e20ab8380b3b85e4f67094dd64a6568fa4ec1dfedb042636996ffecd",
      "size": 67108864,
      "url": "https://mirrorbits.lineageos.org/full/r8q/20250913/boot.img"
    },
    {
      "filename": "dtbo.img",
      "filepath": "/full/r8q/20250913/dtbo.img",
      "sha1": "fd220809730679f1dc0f7b1f43b26166da065e11",
      "sha256": "07e3378abc8d96b6f41addc7849bdaf4d3e9cef4c6586bc9187398c5184d37b4",
      "size": 8388608,
      "url": "https://mirrorbits.lineageos.org/full/r8q/20250913/dtbo.img"
    },
    {
      "filename": "recovery.img",
      "filepath": "/full/r8q/20250913/recovery.img",
      "sha1": "3f190fa6af4930e7a02d1a27d093837cca69d643",
      "sha256": "651de5f6530819cd65b6836cbe886b56e5b578d2b0b46fc527da521e725cf809",
      "size": 82694144,
      "url": "https://mirrorbits.lineageos.org/full/r8q/20250913/recovery.img"
    },
    {
      "filename": "super_empty.img",
      "filepath": "/full/r8q/20250913/super_empty.img",
      "sha1": "061e031e80a7acb9a14d2c7ad59100ae05a444a2",
      "sha256": "a838a43af58bd057e14a4870237667ce9c7539c654bbde64a232ef41867e3125",
      "size": 4644,
      "url": "https://mirrorbits.lineageos.org/full/r8q/20250913/super_empty.img"
    },
    {
      "filename": "vbmeta.img",
      "filepath": "/full/r8q/20250913/vbmeta.img",
      "sha1": "2c1297f39bedf003916502a9ae11ccea3e321042",
      "sha256": "c9a668accdcc6f97fd0b6e47eec39f879e0cebd7d58644482b61412c8f40032c",
      "size": 8192,
      "url": "https://mirrorbits.lineageos.org/full/r8q/20250913/vbmeta.img"
    }
  ],
  "os_patch_level": "2025-08",
  "type": "nightly",
  "version": "22.2"
}
