{
  "date": "2026-01-09",
  "datetime": 1767916800,
  "files": [
    {
      "date": "2026-01-09",
      "datetime": 1767916800,
      "filename": "lineage-22.2-20260109-nightly-sagit-signed.zip",
      "filepath": "/full/sagit/20260109/lineage-22.2-20260109-nightly-sagit-signed.zip",
      "os_patch_level": "2026-01-01",
      "sha1": "4d4a5eb5437b41b155870f654e5d53af47fd147c",
      "sha256": "f0420fd39d7540144575f13ce4fa2e4e76f8ad17037539a2bb8c75e8e0946b62",
      "size": 1033960638,
      "type": "nightly",
      "url": "https://mirrorbits.lineageos.org/full/sagit/20260109/lineage-22.2-20260109-nightly-sagit-signed.zip"
    },
    {
      "filename": "boot.img",
      "filepath": "/full/sagit/20260109/boot.img",
      "sha1": "46f665baeee152efaa2d9e3154a46cdd221bfc35",
      "sha256": "131b218fc35ae276f0b8321900a05094794cfafbf768841ee9ed1ddf4dcb134c",
      "size": 16343040,
      "url": "https://mirrorbits.lineageos.org/full/sagit/20260109/boot.img"
    },
    {
      "filename": "recovery.img",
      "filepath": "/full/sagit/20260109/recovery.img",
      "sha1": "099a3cf33fadd4202867e126f58c070a9f56dbe7",
      "sha256": "7b56123757e99eeb23fe5b51f52181889f3630986855152246cfeaa9c3ea4b43",
      "size": 28180480,
      "url": "https://mirrorbits.lineageos.org/full/sagit/20260109/recovery.img"
    }
  ],
  "os_patch_level": "2026-01-01",
  "type": "nightly",
  "version": "22.2"
}
