{
  "date": "2024-01-30",
  "datetime": 1706572800,
  "files": [
    {
      "date": "2024-01-30",
      "datetime": 1706572800,
      "filename": "lineage-20.0-20240130-nightly-sake-signed.zip",
      "filepath": "/full/sake/20240130/lineage-20.0-20240130-nightly-sake-signed.zip",
      "os_patch_level": "2024-01",
      "sha1": "6e63a73762c66f86955b328328714f10ef647fab",
      "sha256": "78c8fb330e9d240f2f049b38d831e2edb0f942afc468c07b7b4eb05467ae2b28",
      "size": 1171965034,
      "type": "nightly",
      "url": "https://mirrorbits.lineageos.org/full/sake/20240130/lineage-20.0-20240130-nightly-sake-signed.zip"
    },
    {
      "filename": "boot.img",
      "filepath": "/full/sake/20240130/boot.img",
      "sha1": "322657d780a0abb7174e32c29e226af01e68ff7d",
      "sha256": "f6fe07dd149eb9d0bc04728cf4e6fe3f7089e81f240159e4affd962cd742385b",
      "size": 100663296,
      "url": "https://mirrorbits.lineageos.org/full/sake/20240130/boot.img"
    },
    {
      "filename": "dtbo.img",
      "filepath": "/full/sake/20240130/dtbo.img",
      "sha1": "569f1d159a25305927f3eaf11c7b10f87c32dbf6",
      "sha256": "4453d26f21c408330d4dfb058d50147c85740dd76c9faa4507afc6d7aeb5ffc6",
      "size": 25165824,
      "url": "https://mirrorbits.lineageos.org/full/sake/20240130/dtbo.img"
    },
    {
      "filename": "super_empty.img",
      "filepath": "/full/sake/20240130/super_empty.img",
      "sha1": "7232ecaee7ea2b5cc907907d846c30e4aef58617",
      "sha256": "d28ce9044c2c66ad4baf9be2ea6d4c0c774592d69d577e36583c9ed967f7562b",
      "size": 5184,
      "url": "https://mirrorbits.lineageos.org/full/sake/20240130/super_empty.img"
    },
    {
      "filename": "vbmeta.img",
      "filepath": "/full/sake/20240130/vbmeta.img",
      "sha1": "60b0e529f5f610f5d85cc1bda90cdf6786a8f798",
      "sha256": "1c4be6dc5a34511780c75d6a9eb7ced21a579d60e523420730389dd55b21ca0f",
      "size": 8192,
      "url": "https://mirrorbits.lineageos.org/full/sake/20240130/vbmeta.img"
    },
    {
      "filename": "vendor_boot.img",
      "filepath": "/full/sake/20240130/vendor_boot.img",
      "sha1": "d6815ee2b937af182dc9180377b67aa7ce174cad",
      "sha256": "a72f240fe22217e1afd47b8d735a3b5b602b1bd1dfc87e357a303a3ff86f34f4",
      "size": 100663296,
      "url": "https://mirrorbits.lineageos.org/full/sake/20240130/vendor_boot.img"
    }
  ],
  "os_patch_level": "2024-01",
  "type": "nightly",
  "version": "20.0"
}
