{
  "date": "2024-12-01",
  "datetime": 1733011200,
  "files": [
    {
      "date": "2024-12-01",
      "datetime": 1733011200,
      "filename": "lineage-21.0-20241201-nightly-sargo-signed.zip",
      "filepath": "/full/sargo/20241201/lineage-21.0-20241201-nightly-sargo-signed.zip",
      "os_patch_level": "2024-11",
      "sha1": "1cf6ecb331bb27ec5365771e6b51a05bd7ae04b6",
      "sha256": "e4ba8d4deb13880fb8c7469e874ab9dab05727245f24c85db846de945a8c752e",
      "size": 1110908355,
      "type": "nightly",
      "url": "https://mirrorbits.lineageos.org/full/sargo/20241201/lineage-21.0-20241201-nightly-sargo-signed.zip"
    },
    {
      "filename": "boot.img",
      "filepath": "/full/sargo/20241201/boot.img",
      "sha1": "ed14296524a9a8a30b76609af74bf6e537b5a294",
      "sha256": "bc97c85b7b11e1c1b8faf6007a1abf656727784cc18270a84292c07ff5a6a53c",
      "size": 67108864,
      "url": "https://mirrorbits.lineageos.org/full/sargo/20241201/boot.img"
    },
    {
      "filename": "dtbo.img",
      "filepath": "/full/sargo/20241201/dtbo.img",
      "sha1": "53f7e7e3cf6cfbdfdaa7e325877baccf55ebd594",
      "sha256": "09f0f6e436a6f81dcbe7797cfc680d5dcf4718a3de9d99ac96106d30efbf572b",
      "size": 8388608,
      "url": "https://mirrorbits.lineageos.org/full/sargo/20241201/dtbo.img"
    },
    {
      "filename": "super_empty.img",
      "filepath": "/full/sargo/20241201/super_empty.img",
      "sha1": "63bc61d1abc09a2bdc1b1ba606411f889f3facba",
      "sha256": "62024718661d2d02841a0ffc84e63ad815e60a4b3090ffe26e4c70abfab3197b",
      "size": 4656,
      "url": "https://mirrorbits.lineageos.org/full/sargo/20241201/super_empty.img"
    },
    {
      "filename": "vbmeta.img",
      "filepath": "/full/sargo/20241201/vbmeta.img",
      "sha1": "37f8d90b4ebdc1a352ab6995364f15ebbed2678e",
      "sha256": "ba540e057c7e12b2ab489ea4dd1cd71b75fb2fa476ac23a1eeeca25bc612266d",
      "size": 8192,
      "url": "https://mirrorbits.lineageos.org/full/sargo/20241201/vbmeta.img"
    }
  ],
  "os_patch_level": "2024-11",
  "type": "nightly",
  "version": "21.0"
}
