{
  "date": "2025-10-19",
  "datetime": 1760832000,
  "files": [
    {
      "date": "2025-10-19",
      "datetime": 1760832000,
      "filename": "lineage-22.2-20251019-nightly-umi-signed.zip",
      "filepath": "/full/umi/20251019/lineage-22.2-20251019-nightly-umi-signed.zip",
      "os_patch_level": "2025-10",
      "sha1": "9d15cbc848ac4c84881c89e3a377f349fb8a2f5b",
      "sha256": "c3842c11fb4886f4c823fd772aec3d4f6d46b5bc057d379123859e4aa7c22be9",
      "size": 1515381862,
      "type": "nightly",
      "url": "https://mirrorbits.lineageos.org/full/umi/20251019/lineage-22.2-20251019-nightly-umi-signed.zip"
    },
    {
      "filename": "boot.img",
      "filepath": "/full/umi/20251019/boot.img",
      "sha1": "a4059bad4be691c654bab54e3aaa07e5465b71f9",
      "sha256": "4ae0a563b533e846b2d8e11a5dcf647d3b39722023931342ee40d5731b0c3dbb",
      "size": 134217728,
      "url": "https://mirrorbits.lineageos.org/full/umi/20251019/boot.img"
    },
    {
      "filename": "dtbo.img",
      "filepath": "/full/umi/20251019/dtbo.img",
      "sha1": "e76cca9ada91b9e4aa9e700d6c211a8f19e4b57c",
      "sha256": "42b590385dc7c1b25b33079cc25bcdb1ad376bd76424ba8170cc01068d934d01",
      "size": 33554432,
      "url": "https://mirrorbits.lineageos.org/full/umi/20251019/dtbo.img"
    },
    {
      "filename": "recovery.img",
      "filepath": "/full/umi/20251019/recovery.img",
      "sha1": "da224b55c7feca931fe304ef72c652afab2e444d",
      "sha256": "830726ff69eae87ca50e8dce989611960a4a43abbdd7cca0effdbd9e402f10d2",
      "size": 134217728,
      "url": "https://mirrorbits.lineageos.org/full/umi/20251019/recovery.img"
    },
    {
      "filename": "super_empty.img",
      "filepath": "/full/umi/20251019/super_empty.img",
      "sha1": "4bb950f970b176d638d14a318468820f240938cb",
      "sha256": "cbc42814b36e05edf74a58e022485407d42eaba55002fdd802429048819341d8",
      "size": 4644,
      "url": "https://mirrorbits.lineageos.org/full/umi/20251019/super_empty.img"
    },
    {
      "filename": "vbmeta.img",
      "filepath": "/full/umi/20251019/vbmeta.img",
      "sha1": "d78ae688c5d320cba149d2a4886063533a925433",
      "sha256": "426de36698aa19331f2cafcbcaf5e89a1859983ddeaa242ef7fde0eade0cf735",
      "size": 8192,
      "url": "https://mirrorbits.lineageos.org/full/umi/20251019/vbmeta.img"
    }
  ],
  "os_patch_level": "2025-10",
  "type": "nightly",
  "version": "22.2"
}
