{
  "date": "2024-08-16",
  "datetime": 1723766400,
  "files": [
    {
      "date": "2024-08-16",
      "datetime": 1723766400,
      "filename": "lineage-21.0-20240816-nightly-vela-signed.zip",
      "filepath": "/full/vela/20240816/lineage-21.0-20240816-nightly-vela-signed.zip",
      "os_patch_level": "2024-08",
      "sha1": "e232f54203d1a468fb5056fa0307bdd2d511bdbc",
      "sha256": "293adbe709e1efc54300be39f1e9ba87252f65e009edd6ced41be7e7d6aacbf2",
      "size": 1184254248,
      "type": "nightly",
      "url": "https://mirrorbits.lineageos.org/full/vela/20240816/lineage-21.0-20240816-nightly-vela-signed.zip"
    },
    {
      "filename": "boot.img",
      "filepath": "/full/vela/20240816/boot.img",
      "sha1": "6c1bbc1eed500a2bceb43addd823b3789aae6396",
      "sha256": "a6c68deb5889e703e73aa696505f46727da0c7ebbf4c4bbe4ae3c0146cdfa3b5",
      "size": 134217728,
      "url": "https://mirrorbits.lineageos.org/full/vela/20240816/boot.img"
    },
    {
      "filename": "dtbo.img",
      "filepath": "/full/vela/20240816/dtbo.img",
      "sha1": "e89b0722815ff3c83072dcbf7a2ee4be8b4e1429",
      "sha256": "ef21a614fb6a117cdab5e26c1d1c6264390c7b07f8ec84af87188ff04e5f7537",
      "size": 25165824,
      "url": "https://mirrorbits.lineageos.org/full/vela/20240816/dtbo.img"
    },
    {
      "filename": "recovery.img",
      "filepath": "/full/vela/20240816/recovery.img",
      "sha1": "56b94fb9c7012bc92fc78b32a600af18a2a1a731",
      "sha256": "213c72d0925ed353a65d9067758450ce627a38a845798133ff2f8114915eb23d",
      "size": 67108864,
      "url": "https://mirrorbits.lineageos.org/full/vela/20240816/recovery.img"
    },
    {
      "filename": "super_empty.img",
      "filepath": "/full/vela/20240816/super_empty.img",
      "sha1": "c3fa809c333fb2b9ce98d2ee2e2525490d39e839",
      "sha256": "bacc830739789f2d169a8eda7e67b129cab5d8680c4f47cd43c427a6f0fdc678",
      "size": 4772,
      "url": "https://mirrorbits.lineageos.org/full/vela/20240816/super_empty.img"
    },
    {
      "filename": "vbmeta.img",
      "filepath": "/full/vela/20240816/vbmeta.img",
      "sha1": "4c8947bd4feecfba6deb4c5bfd9d32033bb5d986",
      "sha256": "e9de58005eb90c2e72198b7676f9aa623f8c4663ed8efb75c6d07a88f92eb1b8",
      "size": 8192,
      "url": "https://mirrorbits.lineageos.org/full/vela/20240816/vbmeta.img"
    }
  ],
  "os_patch_level": "2024-08",
  "type": "nightly",
  "version": "21.0"
}
