{
  "date": "2026-03-12",
  "datetime": 1773293246,
  "files": [
    {
      "date": "2026-03-12",
      "datetime": 1773293246,
      "filename": "lineage-22.2-20260312-nightly-wade-signed.zip",
      "filepath": "/full/wade/20260312/lineage-22.2-20260312-nightly-wade-signed.zip",
      "os_patch_level": "2026-02-01",
      "sha1": "446ab2b4df21cc6da6ed2a0ebd0ea1a37b516ff5",
      "sha256": "47870fed9d93dc41d6d2c4bb1cab93ac0ac43ac36c72b5357b8d628d34bb10e7",
      "size": 564520454,
      "type": "nightly",
      "url": "https://mirrorbits.lineageos.org/full/wade/20260312/lineage-22.2-20260312-nightly-wade-signed.zip"
    },
    {
      "filename": "boot.img",
      "filepath": "/full/wade/20260312/boot.img",
      "sha1": "37a918e9655bc0aeda42f5b10d882bdccc1b954e",
      "sha256": "375c649f571591c3c8acf130b5b029cb61fac101c59b96b23c0c2614ad2a235d",
      "size": 16777216,
      "url": "https://mirrorbits.lineageos.org/full/wade/20260312/boot.img"
    },
    {
      "filename": "dtb.img",
      "filepath": "/full/wade/20260312/dtb.img",
      "sha1": "6478b7760c21cb91d5eb788274dd9cffaa7b9a52",
      "sha256": "471c866ec9c812eefc2755954c86eca58ad8ceb6317425c4a8f677b1a01cd204",
      "size": 82666,
      "url": "https://mirrorbits.lineageos.org/full/wade/20260312/dtb.img"
    },
    {
      "filename": "dtbo.img",
      "filepath": "/full/wade/20260312/dtbo.img",
      "sha1": "7a9946b1d707c62a76b82ded10ea3eab386de1db",
      "sha256": "41b77ea19e3def666add6a6f1bffdb5432d17206162689334133fab5acb1ae2c",
      "size": 2097152,
      "url": "https://mirrorbits.lineageos.org/full/wade/20260312/dtbo.img"
    },
    {
      "filename": "recovery.img",
      "filepath": "/full/wade/20260312/recovery.img",
      "sha1": "aae72e996bb738c9c07e97046b56f4a5113edecb",
      "sha256": "b3907321aa7d40252a0dfbf3177dfba4904f3e4d9228af65c58db0ef10aa74b9",
      "size": 25165824,
      "url": "https://mirrorbits.lineageos.org/full/wade/20260312/recovery.img"
    },
    {
      "filename": "super_empty.img",
      "filepath": "/full/wade/20260312/super_empty.img",
      "sha1": "767882f605ffadc3d86f73fd895f01541e164cfd",
      "sha256": "1e08fffaa52ba1ce65922903746821490592d70814caf159f682a37c449926f4",
      "size": 4696,
      "url": "https://mirrorbits.lineageos.org/full/wade/20260312/super_empty.img"
    },
    {
      "filename": "vbmeta.img",
      "filepath": "/full/wade/20260312/vbmeta.img",
      "sha1": "d738227f8ed03d88dd474f13c006a95a1976f514",
      "sha256": "da01157dd4027258eef61c5fdd5ffb54d45737654687196654fc243a3cd9b6cd",
      "size": 8192,
      "url": "https://mirrorbits.lineageos.org/full/wade/20260312/vbmeta.img"
    }
  ],
  "os_patch_level": "2026-02-01",
  "type": "nightly",
  "version": "22.2"
}
